paraphrase_googletranslate/__init__.py
paraphrase_googletranslate/paraphraser.py
paraphrase_googletranslate-0.0.7.dist-info/LICENSE
paraphrase_googletranslate-0.0.7.dist-info/METADATA
paraphrase_googletranslate-0.0.7.dist-info/WHEEL
paraphrase_googletranslate-0.0.7.dist-info/top_level.txt
paraphrase_googletranslate-0.0.7.dist-info/RECORD
