Metadata-Version: 2.1
Name: paraphrase-googletranslate
Version: 0.0.7
Summary: paraphrase_googletranslate
Home-page: https://github.com/kkristof200/py_paraphrase_googletranslate
Author: Kristóf-Attila Kovács
License: UNKNOWN
Platform: UNKNOWN
Classifier: Programming Language :: Python :: 3.4
Classifier: Programming Language :: Python :: 3.5
Classifier: Programming Language :: Python :: 3.6
Classifier: Programming Language :: Python :: 3.7
Classifier: Programming Language :: Python :: 3.8
Classifier: Programming Language :: Python :: 3.9
Classifier: License :: OSI Approved :: MIT License
Classifier: Operating System :: OS Independent
Requires-Python: >=3.4
License-File: LICENSE
Requires-Dist: google-trans-new (>=1.1.9)
